tap_sleeper/__init__.py
tap_sleeper/schemas/__init__.py
tap_sleeper/schemas/league.py
tap_sleeper/schemas/players.py
tap_sleeper/schemas/sport_state.py
tap_sleeper/streams.py
tap_sleeper/tap.py
tap_sleeper/tests/__init__.py
tap_sleeper/tests/test_core.py
tap_sleeper-0.5.3.dist-info/METADATA
tap_sleeper-0.5.3.dist-info/WHEEL
tap_sleeper-0.5.3.dist-info/entry_points.txt
tap_sleeper-0.5.3.dist-info/RECORD
