Metadata-Version: 2.1
Name: tap-sleeper
Version: 0.5.3
Summary: `tap-sleeper` is a Singer tap for Sleeper, built with the Meltano SDK for Singer Taps.
Home-page: https://github.com/collinprather/tap-sleeper
License: Apache 2.0
Keywords: ELT,Sleeper,Football
Author: Collin Prather
Requires-Python: >=3.8,<3.12
Classifier: License :: Other/Proprietary License
Classifier: Programming Language :: Python :: 3
Classifier: Programming Language :: Python :: 3.8
Classifier: Programming Language :: Python :: 3.9
Classifier: Programming Language :: Python :: 3.10
Classifier: Programming Language :: Python :: 3.11
Requires-Dist: singer-sdk (>=0.35.0,<0.36.0)
Project-URL: Repository, https://github.com/collinprather/tap-sleeper
